alpha_v2/__init__.py
alpha_v2/src/__init__.py
alpha_v2/src/utils.py
alpha_v2/src/data/__init__.py
alpha_v2/src/data/get_data.py
alpha_v2/src/data/preprocess.py
alpha_v2/src/data/split_dataset.py
alpha_v2/src/data/utils.py
alpha_v2/src/evaluate/__init__.py
alpha_v2/src/evaluate/evaluate.py
alpha_v2/src/ocn/__init__.py
alpha_v2/src/ocn/ocn.py
alpha_v2/src/optuna/__init__.py
alpha_v2/src/optuna/objective.py
alpha_v2/src/optuna/utils.py
demo_alphav2-2.0.1.dist-info/LICENSE
demo_alphav2-2.0.1.dist-info/METADATA
demo_alphav2-2.0.1.dist-info/WHEEL
demo_alphav2-2.0.1.dist-info/top_level.txt
demo_alphav2-2.0.1.dist-info/RECORD
