Metadata-Version: 2.1
Name: demo_alphav2
Version: 2.0.1
Summary: A package of alphav2
Home-page: https://github.com/quandn2003/demo_package_alphav2
License: MIT
Classifier: License :: OSI Approved :: MIT License
Classifier: Programming Language :: Python :: 3.10
Classifier: Operating System :: OS Independent
Requires-Python: >=3.10
License-File: LICENSE
